DictMaper/__init__.py
DictMaper/map_dict.py
DictMaper/utils.py
dictmaper-0.0.6.dist-info/DESCRIPTION.rst
dictmaper-0.0.6.dist-info/METADATA
dictmaper-0.0.6.dist-info/RECORD
dictmaper-0.0.6.dist-info/WHEEL
dictmaper-0.0.6.dist-info/metadata.json
dictmaper-0.0.6.dist-info/top_level.txt
test/__init__.py
test/test_generate_maper.py
