Metadata-Version: 2.0
Name: dictmaper
Version: 0.0.6
Summary: Library created to map keys in dictionaries.
Home-page: UNKNOWN
Author: Arnold Blandon and Santiago Gonzalez
Author-email: arnold.blandon1@gmail.com
Maintainer: Santiago Gonzalez
Maintainer-email: alejandro980619@outlook.com
License: UNKNOWN
Keywords: python,dict,map,data
Platform: UNKNOWN
Classifier: Development Status :: 1 - Planning
Classifier: Intended Audience :: Developers
Classifier: Programming Language :: Python :: 3
Classifier: Operating System :: Unix
Classifier: Operating System :: MacOS :: MacOS X
Classifier: Operating System :: Microsoft :: Windows
